adsms/__init__.py
adsms-0.5.dist-info/LICENSE
adsms-0.5.dist-info/METADATA
adsms-0.5.dist-info/WHEEL
adsms-0.5.dist-info/entry_points.txt
adsms-0.5.dist-info/top_level.txt
adsms-0.5.dist-info/RECORD
