Metadata-Version: 2.1
Name: adsms
Version: 0.5
Summary: Send SMS aircraft alerts based on ADS-B data
Author-email: Samuel Sloniker <sam@kj7rrv.com>
Project-URL: Homepage, https://git.kj7rrv.com/kj7rrv/adsms
Classifier: Programming Language :: Python
Classifier: Programming Language :: Python :: 3
Classifier: Development Status :: 2 - Pre-Alpha
Classifier: License :: OSI Approved :: GNU Affero General Public License v3
Requires-Python: >=3.7
License-File: LICENSE
Requires-Dist: requests
